ovos_PHAL_plugin_homeassistant/__init__.py
ovos_PHAL_plugin_homeassistant/version.py
ovos_PHAL_plugin_homeassistant/logic/__init__.py
ovos_PHAL_plugin_homeassistant/logic/connector.py
ovos_PHAL_plugin_homeassistant/logic/device.py
ovos_PHAL_plugin_homeassistant/logic/integration.py
ovos_PHAL_plugin_homeassistant/logic/socketclient.py
ovos_PHAL_plugin_homeassistant/logic/utils.py
ovos_PHAL_plugin_homeassistant/ui/Dashboard.qml
ovos_PHAL_plugin_homeassistant/ui/DeviceControlsLoader.qml
ovos_PHAL_plugin_homeassistant/ui/InstanceGridButton.qml
ovos_PHAL_plugin_homeassistant/ui/InstanceSetup.qml
ovos_PHAL_plugin_homeassistant/ui/InstanceSetupFooterButtons.qml
ovos_PHAL_plugin_homeassistant/ui/+mediacenter/Dashboard.qml
ovos_PHAL_plugin_homeassistant/ui/+mediacenter/InstanceSetup.qml
ovos_PHAL_plugin_homeassistant/ui/code/helper.js
ovos_PHAL_plugin_homeassistant/ui/dashcards/AutomationCard.qml
ovos_PHAL_plugin_homeassistant/ui/dashcards/BinarySensorCard.qml
ovos_PHAL_plugin_homeassistant/ui/dashcards/CameraCard.qml
ovos_PHAL_plugin_homeassistant/ui/dashcards/CircleSensorItemPercentType.qml
ovos_PHAL_plugin_homeassistant/ui/dashcards/LightCard.qml
ovos_PHAL_plugin_homeassistant/ui/dashcards/MediaPlayerCard.qml
ovos_PHAL_plugin_homeassistant/ui/dashcards/PowerSensorItemType.qml
ovos_PHAL_plugin_homeassistant/ui/dashcards/SceneCard.qml
ovos_PHAL_plugin_homeassistant/ui/dashcards/SensorCard.qml
ovos_PHAL_plugin_homeassistant/ui/dashcards/SwitchCard.qml
ovos_PHAL_plugin_homeassistant/ui/dashcards/VacuumCard.qml
ovos_PHAL_plugin_homeassistant/ui/delegates/DashboardDelegate.qml
ovos_PHAL_plugin_homeassistant/ui/delegates/DeviceDashboardDelegate.qml
ovos_PHAL_plugin_homeassistant/ui/devicecontrols/ColorPickerControl.qml
ovos_PHAL_plugin_homeassistant/ui/devicecontrols/LightBrightness.qml
ovos_PHAL_plugin_homeassistant/ui/devicecontrols/LightColor.qml
ovos_PHAL_plugin_homeassistant/ui/devicecontrols/LightDeviceStateButton.qml
ovos_PHAL_plugin_homeassistant-0.1.0.dist-info/LICENSE
ovos_PHAL_plugin_homeassistant-0.1.0.dist-info/METADATA
ovos_PHAL_plugin_homeassistant-0.1.0.dist-info/WHEEL
ovos_PHAL_plugin_homeassistant-0.1.0.dist-info/entry_points.txt
ovos_PHAL_plugin_homeassistant-0.1.0.dist-info/top_level.txt
ovos_PHAL_plugin_homeassistant-0.1.0.dist-info/zip-safe
ovos_PHAL_plugin_homeassistant-0.1.0.dist-info/RECORD
