Metadata-Version: 2.1
Name: ovos-PHAL-plugin-homeassistant
Version: 0.1.0
Summary: Homeassistant PHAL plugin for OpenVoiceOS
Home-page: https://github.com/OpenVoiceOS/ovos-PHAL-plugin-homeassistant
Author: Aiix
Author-email: aix.m@outlook.com
License: Apache-2.0
Classifier: Development Status :: 3 - Alpha
Classifier: Intended Audience :: Developers
Classifier: Topic :: Utilities
Classifier: License :: OSI Approved :: Apache Software License
Classifier: Programming Language :: Python :: 3.5
Classifier: Programming Language :: Python :: 3.6
Classifier: Programming Language :: Python :: 3.7
Classifier: Programming Language :: Python :: 3.8
Classifier: Programming Language :: Python :: 3.9
Classifier: Programming Language :: Python :: 3.10
License-File: LICENSE
Requires-Dist: ovos-plugin-manager>=0.0.23
Requires-Dist: ovos-utils>=0.0.27
Requires-Dist: ovos-config>=0.0.5
Requires-Dist: ovos-PHAL-plugin-oauth>=0.0.3
Requires-Dist: ovos-bus-client>=0.0.8
Requires-Dist: youtube-search~=2.1
Requires-Dist: pytube~=12.1
Requires-Dist: websockets<14.0,>=0.54.0
Requires-Dist: nested-lookup~=0.2
Requires-Dist: webcolors~=1.13
Requires-Dist: websocket-client<2.0.0,>=0.54.0
